LightningBO/__init__.py
LightningBO/bayesian_core.py
LightningBO/bayesian_optimization.py
lightningbo-0.1.2.dist-info/licenses/LICENSE
lightningbo-0.1.2.dist-info/METADATA
lightningbo-0.1.2.dist-info/WHEEL
lightningbo-0.1.2.dist-info/top_level.txt
lightningbo-0.1.2.dist-info/RECORD
