Metadata-Version: 2.4
Name: LightningBO
Version: 0.1.2
Summary: LightningBO: JAXベースの高速ベイジアン最適化ライブラリ。ハイパーパラメータ探索やマーケティング最適化に最適。EI/PI/UCB/LCB獲得関数、ガウス過程、JIT高速化、メモリ効率設計。
Author-email: s-ohtake <s.ohtake@cartahd.com>
License-Expression: Apache-2.0
Project-URL: Homepage, https://github.com/s-ohtake/LightningBO
Project-URL: Repository, https://github.com/s-ohtake/LightningBO
Project-URL: Documentation, https://github.com/s-ohtake/LightningBO/blob/main/docs/LightningBO.ipynb
Keywords: bayesian optimization,jax,hyperparameter,machine learning,marketing mix
Classifier: Programming Language :: Python :: 3.13
Classifier: Operating System :: OS Independent
Classifier: Intended Audience :: Science/Research
Classifier: Topic :: Scientific/Engineering :: Artificial Intelligence
Classifier: Topic :: Software Development :: Libraries :: Python Modules
Requires-Python: >=3.12
License-File: LICENSE
Requires-Dist: jax
Requires-Dist: jaxlib
Requires-Dist: optax
Requires-Dist: numpy
Requires-Dist: absl-py
Requires-Dist: pytest
Requires-Dist: matplotlib
Dynamic: license-file
